readExcel/__init__.py
readExcel/readExcelDataWithXlrd.py
readExcel/readExcelWithOpenpyxl.py
readExcel/readExcelWithPandas.py
readExcel/readFilesWithXlwings.py
readExcelFiles-1.0.1.dist-info/METADATA
readExcelFiles-1.0.1.dist-info/WHEEL
readExcelFiles-1.0.1.dist-info/top_level.txt
readExcelFiles-1.0.1.dist-info/RECORD
